adt_clients/__init__.py
adt_clients/analytic_dataset_client.py
adt_clients/analytic_dataset_definition_client.py
adt_clients/models.py
adt_clients-2.3.7.dist-info/LICENSE.txt
adt_clients-2.3.7.dist-info/METADATA
adt_clients-2.3.7.dist-info/WHEEL
adt_clients-2.3.7.dist-info/top_level.txt
adt_clients-2.3.7.dist-info/RECORD
